setup.cfg
setup.py
alchemist/__init__.py
alchemist/_version.py
alchemist/app.py
alchemist/exceptions.py
alchemist/management.py
alchemist/plugin.py
alchemist/test.py
alchemist/utils.py
alchemist.egg-info/PKG-INFO
alchemist.egg-info/SOURCES.txt
alchemist.egg-info/dependency_links.txt
alchemist.egg-info/entry_points.txt
alchemist.egg-info/requires.txt
alchemist.egg-info/top_level.txt
alchemist/commands/__init__.py
alchemist/commands/db.py
alchemist/commands/load.py
alchemist/commands/server.py
alchemist/commands/settings.py
alchemist/commands/shell.py
alchemist/commands/test.py
alchemist/conf/__init__.py
alchemist/conf/default_settings.py
alchemist/db/__init__.py
alchemist/db/_engine.py
alchemist/db/_session.py
alchemist/db/model.py
alchemist/db/query.py
alchemist/db/operations/__init__.py
alchemist/db/operations/shell.py
alchemist/db/operations/sql.py
alchemist/db/operations/utils.py
alchemist/tests/__init__.py
alchemist/tests/test_app.py
alchemist/tests/test_commands.py
alchemist/tests/test_conf.py
alchemist/tests/test_db.py
alchemist/tests/test_management.py
alchemist/tests/utils.py
alchemist/tests/a/__init__.py
alchemist/tests/a/app.py
alchemist/tests/a/example.py
alchemist/tests/a/models.py
alchemist/tests/a/settings.py
alchemist/tests/a/b/__init__.py
alchemist/tests/a/b/app.py
alchemist/tests/a/b/example.py
alchemist/tests/a/b/models.py
alchemist/tests/a/b/settings.py