Metadata-Version: 1.1
Name: alchemist
Version: 0.3.1
Summary: A server architecture built on top of a solid foundation provided by flask, sqlalchemy, and various extensions.
Home-page: http://github.com/concordusapps/alchemist
Author: Concordus Applications
Author-email: support@concordusapps.com
License: UNKNOWN
Platform: UNKNOWN
Classifier: Development Status :: 3 - Alpha
Classifier: Framework :: Flask
Classifier: Intended Audience :: Developers
Classifier: Intended Audience :: System Administrators
Classifier: License :: OSI Approved :: MIT License
Classifier: Operating System :: OS Independent
Classifier: Programming Language :: Python :: 2.7
Classifier: Programming Language :: Python :: 3.3
Classifier: Topic :: Software Development :: Libraries :: Python Modules
Classifier: Topic :: Utilities
